tester/__init__.py
tester/__main__.py
tester/compiler.py
tester/features.py
tester/lang.py
tester/testmanip.py
tester/config/tags.json
tests/__init__.py
tests/compiler.py
tests/features.py
tests/testmanip.py
vival-3.5.0.dist-info/METADATA
vival-3.5.0.dist-info/WHEEL
vival-3.5.0.dist-info/dependency_links.txt
vival-3.5.0.dist-info/entry_points.txt
vival-3.5.0.dist-info/top_level.txt
vival-3.5.0.dist-info/RECORD
