Metadata-Version: 2.1
Name: vival
Version: 3.5.0
Summary: A simple commandline app for testing standard input/output applications.
Home-page: https://github.com/ViktorooReps/vival
Author: Viktor Scherbakov
Author-email: viktoroo.sch@gmail.com
License: MIT
Download-URL: https://github.com/ViktorooReps/vival/archive/1.0.0.tar.gz
Platform: UNKNOWN
Classifier: License :: OSI Approved :: MIT License
Classifier: Programming Language :: Python :: 2.7
Classifier: Programming Language :: Python :: 3
Classifier: Programming Language :: Python :: 3.7
Requires-Python: >=3.8
Requires-Dist: click (~=7.1.2)
Requires-Dist: tqdm (~=4.57.0)
Requires-Dist: pydantic (~=1.8.2)
Requires-Dist: setuptools (~=52.0.0)
